odoo/addons/project_forecast_task_type/__init__.py
odoo/addons/project_forecast_task_type/__manifest__.py
odoo/addons/project_forecast_task_type/models/__init__.py
odoo/addons/project_forecast_task_type/models/project_task.py
odoo/addons/project_forecast_task_type/models/project_task_type.py
odoo/addons/project_forecast_task_type/views/project_task_type.xml
odoo_addon_project_forecast_task_type-16.0.1.0.2.dist-info/METADATA
odoo_addon_project_forecast_task_type-16.0.1.0.2.dist-info/WHEEL
odoo_addon_project_forecast_task_type-16.0.1.0.2.dist-info/top_level.txt
odoo_addon_project_forecast_task_type-16.0.1.0.2.dist-info/RECORD
