Metadata-Version: 2.1
Name: odoo-addon-project_forecast_task_type
Version: 16.0.1.0.2
Summary: Project Forecast Filter by Task Stages (project.task.type)
Home-page: https://github.com/OCA/project
Author: Coopdevs, Odoo Community Association (OCA)
Author-email: support@odoo-community.org
License: AGPL-3
Classifier: Programming Language :: Python
Classifier: Framework :: Odoo
Classifier: Framework :: Odoo :: 16.0
Classifier: License :: OSI Approved :: GNU Affero General Public License v3
Classifier: Development Status :: 3 - Alpha
Requires-Python: >=3.10
Requires-Dist: odoo-addon-project-forecast-line<16.1dev,>=16.0dev
Requires-Dist: odoo<16.1dev,>=16.0a
